retis-1.6.3.dist-info/METADATA
retis-1.6.3.dist-info/WHEEL
retis-1.6.3.dist-info/licenses/LICENSE
retis/__init__.py
retis/retis.abi3.so
retis-1.6.3.dist-info/RECORD
