Metadata-Version: 2.4
Name: retis
Version: 1.6.3
Classifier: Development Status :: 4 - Beta
Classifier: Intended Audience :: Developers
Classifier: Operating System :: POSIX :: Linux
Classifier: Programming Language :: Python :: 3
Classifier: Programming Language :: Python :: 3.8
Classifier: Programming Language :: Python :: 3.9
Classifier: Programming Language :: Python :: 3.10
Classifier: Programming Language :: Python :: 3.11
Classifier: Programming Language :: Python :: 3.12
Classifier: Programming Language :: Python :: 3.13
Classifier: Programming Language :: Python
Classifier: Programming Language :: Rust
Classifier: License :: OSI Approved :: GNU General Public License v2 (GPLv2)
License-File: LICENSE
Summary: Python bindings for Retis events
Home-Page: https://github.com/retis-org/retis-org
Project-URL: HomePage, https://github.com/retis-org/retis
Project-URL: Documentation, https://retis.readthedocs.io/
Project-URL: Repository, https://github.com/retis-org/retis
